ann/ANNFaiss.py
ann/ANNMilvus.py
ann/MilvusANN.py
ann/__init__.py
ann/utils.py
ann/utils/__init__.py
ann/utils/data_processor_utils.py
ann/utils/logger.py
fast_ann-2020.4.27.15.5.40.dist-info/METADATA
fast_ann-2020.4.27.15.5.40.dist-info/RECORD
fast_ann-2020.4.27.15.5.40.dist-info/WHEEL
fast_ann-2020.4.27.15.5.40.dist-info/entry_points.txt
fast_ann-2020.4.27.15.5.40.dist-info/top_level.txt
