Metadata-Version: 2.1
Name: fast-ann
Version: 2020.4.27.15.5.40
Summary: description
Home-page: https://github.com/Jie-Yuan/tql-ANN
Author: JieYuan
Author-email: 313303303@qq.com
Maintainer: JieYuan
Maintainer-email: 313303303@qq.com
License: MIT
Keywords: tool wheel,yuanjie,utils
Platform: all
Classifier: Operating System :: OS Independent
Classifier: Intended Audience :: Developers
Classifier: License :: OSI Approved :: MIT License
Classifier: Programming Language :: Python
Classifier: Programming Language :: Python :: Implementation
Requires-Python: >=3.5
